cnstd/__init__.py
cnstd/__version__.py
cnstd/app.py
cnstd/cli.py
cnstd/cn_std.py
cnstd/consts.py
cnstd/detector.py
cnstd/lr_scheduler.py
cnstd/trainer.py
cnstd/yolo_detector.py
cnstd/datasets/__init__.py
cnstd/datasets/dataset.py
cnstd/datasets/util.py
cnstd/model/__init__.py
cnstd/model/base.py
cnstd/model/core.py
cnstd/model/dbnet.py
cnstd/model/fpn.py
cnstd/ppocr/__init__.py
cnstd/ppocr/angle_classifier.py
cnstd/ppocr/consts.py
cnstd/ppocr/img_operators.py
cnstd/ppocr/opt_utils.py
cnstd/ppocr/pp_detector.py
cnstd/ppocr/predict_rec.py
cnstd/ppocr/predict_system.py
cnstd/ppocr/rapid_detector.py
cnstd/ppocr/utility.py
cnstd/ppocr/postprocess/__init__.py
cnstd/ppocr/postprocess/cls_postprocess.py
cnstd/ppocr/postprocess/db_postprocess.py
cnstd/ppocr/postprocess/east_postprocess.py
cnstd/ppocr/postprocess/locality_aware_nms.py
cnstd/ppocr/postprocess/pg_postprocess.py
cnstd/ppocr/postprocess/rec_postprocess.py
cnstd/ppocr/postprocess/sast_postprocess.py
cnstd/ppocr/postprocess/pse_postprocess/__init__.py
cnstd/ppocr/postprocess/pse_postprocess/pse_postprocess.py
cnstd/ppocr/postprocess/pse_postprocess/pse/__init__.py
cnstd/ppocr/postprocess/pse_postprocess/pse/setup.py
cnstd/transforms/__init__.py
cnstd/transforms/base.py
cnstd/transforms/process_data.py
cnstd/transforms/random_crop.py
cnstd/transforms/resize.py
cnstd/transforms/utils.py
cnstd/utils/__init__.py
cnstd/utils/_utils.py
cnstd/utils/common_types.py
cnstd/utils/geometry.py
cnstd/utils/metrics.py
cnstd/utils/repr.py
cnstd/utils/utils.py
cnstd/yolov7/__init__.py
cnstd/yolov7/autoanchor.py
cnstd/yolov7/common.py
cnstd/yolov7/consts.py
cnstd/yolov7/datasets.py
cnstd/yolov7/experimental.py
cnstd/yolov7/general.py
cnstd/yolov7/layout_analyzer.py
cnstd/yolov7/loss.py
cnstd/yolov7/metrics.py
cnstd/yolov7/plots.py
cnstd/yolov7/torch_utils.py
cnstd/yolov7/yolo.py
cnstd/yolov7/yolov7-mfd.yaml
cnstd/yolov7/yolov7-tiny-layout.yaml
cnstd/yolov7/yolov7-tiny-mfd.yaml
cnstd-1.2.6.1.data/data/yolov7-mfd.yaml
cnstd-1.2.6.1.dist-info/LICENSE
cnstd-1.2.6.1.dist-info/METADATA
cnstd-1.2.6.1.dist-info/WHEEL
cnstd-1.2.6.1.dist-info/entry_points.txt
cnstd-1.2.6.1.dist-info/top_level.txt
cnstd-1.2.6.1.dist-info/RECORD
