Metadata-Version: 2.1
Name: cnstd
Version: 1.2.6.1
Summary: Python3 package for Chinese/English Scene Text Detection (STD), Mathematical Formula Detection (MFD), and Layout Analysis, with free pretrained models
Home-page: https://github.com/breezedeus/cnstd
Author: breezedeus
Author-email: breezedeus@163.com
License: Apache 2.0
Platform: Mac
Platform: Linux
Platform: Windows
Classifier: Development Status :: 4 - Beta
Classifier: Operating System :: OS Independent
Classifier: Intended Audience :: Developers
Classifier: License :: OSI Approved :: Apache Software License
Classifier: Programming Language :: Python
Classifier: Programming Language :: Python :: Implementation
Classifier: Programming Language :: Python :: 3
Classifier: Programming Language :: Python :: 3.7
Classifier: Programming Language :: Python :: 3.8
Classifier: Programming Language :: Python :: 3.9
Classifier: Programming Language :: Python :: 3.10
Classifier: Topic :: Scientific/Engineering :: Artificial Intelligence
License-File: LICENSE
Requires-Dist: click
Requires-Dist: tqdm
Requires-Dist: pyyaml
Requires-Dist: unidecode
Requires-Dist: torch>=1.8.0
Requires-Dist: torchvision>=0.9.0
Requires-Dist: numpy
Requires-Dist: scipy
Requires-Dist: pandas
Requires-Dist: pytorch-lightning
Requires-Dist: pillow>=5.3.0
Requires-Dist: opencv-python>=4.0.0
Requires-Dist: shapely
Requires-Dist: pyclipper
Requires-Dist: matplotlib
Requires-Dist: seaborn
Requires-Dist: onnx
Requires-Dist: huggingface-hub
Requires-Dist: ultralytics
Requires-Dist: rapidocr>=3.0
Provides-Extra: dev
Requires-Dist: pip-tools; extra == "dev"
Requires-Dist: pytest; extra == "dev"
Provides-Extra: ort-cpu
Requires-Dist: onnxruntime; extra == "ort-cpu"
Provides-Extra: ort-gpu
Requires-Dist: onnxruntime-gpu; extra == "ort-gpu"
